Metadata-Version: 2.1
Name: dependency-package-katiezhao
Version: 0.0.2
Summary: A package used for dependency for katiezhao
Home-page: https://github.com/insomniapx-python-projects/py_package.git
Author: katiezhao
Author-email: katieyangzhao@gmail.com
License: UNKNOWN
Platform: UNKNOWN
Requires-Python: >=3.6
License-File: LICENSE
Requires-Dist: pytest (==6.2.4)
Requires-Dist: numpy (==1.20.3)
